[{"id": "Q968388", "name": "Roger Camille", "imageUrl": "http://commons.wikimedia.org/wiki/Special:FilePath/Kiko%2019951003.jpg?width=300", "birthYear": 1936, "profession": "illustrator", "professionDisplay": "Illustrator", "deathYear": 2006}, {"id": "Q16014157", "name": "Ivy May Pearce", "imageUrl": "http://commons.wikimedia.org/wiki/Special:FilePath/Ivy%20May%20Pearce%20%281936%29.jpg?width=300", "birthYear": 1914, "profession": "aircraft pilot", "professionDisplay": "Aircraft Pilot", "deathYear": 1998}, {"id": "Q3525991", "name": "Cyril Washbrook", "imageUrl": "http://commons.wikimedia.org/wiki/Special:FilePath/Cyril%20Washbrook%201951.jpg?width=300", "birthYear": 1914, "profession": "cricketer", "professionDisplay": "Cricketer", "deathYear": 1999}, {"id": "Q128976", "name": "Alec Douglas-Home", "imageUrl": "http://commons.wikimedia.org/wiki/Special:FilePath/Alec%20Douglas-Home%20%28c1963%29.jpg?width=300", "birthYear": 1903, "profession": "politician", "professionDisplay": "Politician", "deathYear": 1995}, {"id": "Q12627093", "name": "Antun Mitrovi\u0107", "imageUrl": "http://commons.wikimedia.org/wiki/Special:FilePath/Antun%20Mitrovi%C4%87-01-02.jpg?width=300", "birthYear": 1920, "profession": "racing driver", "professionDisplay": "Racing Driver", "deathYear": 1996}, {"id": "Q62515", "name": "Gunter Sachs", "imageUrl": "http://commons.wikimedia.org/wiki/Special:FilePath/Gunter%20Sachs%20-%20ETH-BIB%20-%20Com%20C20-028-088-002.jpg?width=300", "birthYear": 1932, "profession": "photographer", "professionDisplay": "Photographer", "deathYear": 2011, "causeOfDeath": "gunshot wound", "causeCategory": "violence"}, {"id": "Q1130539", "name": "Georg Littasy", "imageUrl": "http://commons.wikimedia.org/wiki/Special:FilePath/Littasy%20Gy%C3%B6rgy.JPG?width=300", "birthYear": 1912, "profession": "opera singer", "professionDisplay": "Opera Singer", "deathYear": 1996}, {"id": "Q45512", "name": "Manfred Deix", "imageUrl": "http://commons.wikimedia.org/wiki/Special:FilePath/%C3%96sterreichischer%20Kabarettpreis%202012%2049%20Manfred%20Deix.jpg?width=300", "birthYear": 1949, "profession": "writer", "professionDisplay": "Writer", "deathYear": 2016}, {"id": "Q4990056", "name": "Petra Wadstr\u00f6m", "imageUrl": "http://commons.wikimedia.org/wiki/Special:FilePath/Petra%20Wadstr%C3%B6m%2001.jpg?width=300", "birthYear": 1952, "profession": "inventor", "professionDisplay": "Inventor"}, {"id": "Q252094", "name": "Igor Vulokh", "imageUrl": "http://commons.wikimedia.org/wiki/Special:FilePath/Igor%20Vulokh%20Portrait.jpg?width=300", "birthYear": 1938, "profession": "painter", "professionDisplay": "Painter", "deathYear": 2012}]